AkumaImageEffect/__init__.py
AkumaImageEffect/effect_engine.py
AkumaImageEffect/effects/core_effects.py
AkumaImageEffect/main.py
akumaimageeffect-0.1.2.dist-info/LICENSE
akumaimageeffect-0.1.2.dist-info/METADATA
akumaimageeffect-0.1.2.dist-info/WHEEL
akumaimageeffect-0.1.2.dist-info/RECORD
