Metadata-Version: 2.3
Name: akumaimageeffect
Version: 0.1.2
Summary: A Python project for image effects
License: MIT
Author: akumanomi1988
Author-email: akumanomi1988@gmail.com
Requires-Python: >=3.10,<4.0
Classifier: License :: OSI Approved :: MIT License
Classifier: Programming Language :: Python :: 3
Classifier: Programming Language :: Python :: 3.10
Classifier: Programming Language :: Python :: 3.11
Classifier: Programming Language :: Python :: 3.12
Classifier: Programming Language :: Python :: 3.13
Requires-Dist: Pillow (>=8.0.0,<9.0.0)
Requires-Dist: opencv-python (>=4.11,<5.0)
